README.rst
setup.py
mole/__init__.py
mole/element.py
mole/event.py
mole/planner.py
mole.egg-info/PKG-INFO
mole.egg-info/SOURCES.txt
mole.egg-info/dependency_links.txt
mole.egg-info/entry_points.txt
mole.egg-info/requires.txt
mole.egg-info/top_level.txt
mole/action/__init__.py
mole/action/a.py
mole/action/avg.py
mole/action/b.py
mole/action/count.py
mole/action/dedup.py
mole/action/fields.py
mole/action/head.py
mole/action/input.py
mole/action/max.py
mole/action/min.py
mole/action/output.py
mole/action/parser.py
mole/action/rename.py
mole/action/search.py
mole/action/set.py
mole/action/sort.py
mole/action/sum.py
mole/action/tail.py
mole/action/timesearch.py
mole/action/timespan.py
mole/action/transaction.py
mole/action/uniq.py
mole/client/__init__.py
mole/client/basic.py
mole/helper/__init__.py
mole/helper/config.py
mole/helper/eval.py
mole/helper/log.py
mole/helper/netstring.py
mole/helper/process.py
mole/helper/timeformat.py
mole/index/__init__.py
mole/index/basic.py
mole/index/whoosh.py
mole/input/__init__.py
mole/input/_tail.py
mole/input/basic.py
mole/input/file.py
mole/input/network.py
mole/input/tail.py
mole/output/__init__.py
mole/output/basic.py
mole/output/iterator.py
mole/output/serialize.py
mole/output/values.py
mole/parser/__init__.py
mole/parser/basic.py
mole/parser/regex.py
mole/plotter/__init__.py
mole/plotter/basic.py
mole/plotter/network.py
mole/plotter/regex.py
mole/script/__init__.py
mole/script/client.py
mole/script/indexer.py
mole/script/seeker.py
mole/server/__init__.py
mole/server/index.py
mole/server/seeker.py