Metadata-Version: 1.1
Name: mole
Version: 0.1
Summary: A flexible log analyzer and operational intelligence tool.
Home-page: http://github.com/ajdiaz/mole
Author: Andres J. Diaz
Author-email: ajdiaz@connectical.com
License: GPLv2
Platform: UNKNOWN
Classifier: Development Status :: 4 - Beta
Classifier: Intended Audience :: Developers
Classifier: License :: OSI Approved :: GNU General Public License (GPL)
Classifier: Operating System :: OS Independent
Classifier: Programming Language :: Python
Classifier: Programming Language :: Python :: 2.7
Classifier: Programming Language :: Python :: 2.6
Classifier: Natural Language :: English
